aivk_fs/__about__.py
aivk_fs/__init__.py
aivk_fs/fs.py
aivk_fs/onCli/__init__.py
aivk_fs/onCli/__main__.py
aivk_fs/onInstall/__init__.py
aivk_fs/onInstall/__main__.py
aivk_fs/onLoad/__init__.py
aivk_fs/onLoad/__main__.py
aivk_fs/onUpdate/__init__.py
aivk_fs/onUpdate/__main__.py
aivk_fs-0.0.1.dist-info/METADATA
aivk_fs-0.0.1.dist-info/WHEEL
aivk_fs-0.0.1.dist-info/entry_points.txt
aivk_fs-0.0.1.dist-info/licenses/LICENSE
aivk_fs-0.0.1.dist-info/RECORD
